README.md
setup.py
mongodbatlas/__init__.py
mongodbatlas/__main__.py
mongodbatlas/atlasapi.py
mongodbatlas/atlascli.py
mongodbatlas/atlascluster.py
mongodbatlas/atlascommand.py
mongodbatlas/atlaserrors.py
mongodbatlas/atlaskey.py
mongodbatlas/atlasorganization.py
mongodbatlas/atlasproject.py
mongodbatlas/atlasrequests.py
mongodbatlas/atlasresource.py
mongodbatlas/command.py
mongodbatlas/createcommand.py
mongodbatlas/errors.py
mongodbatlas/opcapi.py
mongodbatlas/outputformat.py
mongodbatlas/requestgroup.py
mongodbatlas/version.py
mongodbatlas.egg-info/PKG-INFO
mongodbatlas.egg-info/SOURCES.txt
mongodbatlas.egg-info/dependency_links.txt
mongodbatlas.egg-info/entry_points.txt
mongodbatlas.egg-info/requires.txt
mongodbatlas.egg-info/top_level.txt
test/__init__.py
test/pause_resume.py
test/test_api.py
test/test_atlas_apimixin.py
test/test_atlasapi.py
test/test_atlascluster.py
test/test_atlaskey.py
test/test_atlasproject.py