Metadata-Version: 2.1
Name: mongodbatlas
Version: 0.2.6
Summary: Python API to the MongoDB Atlas REST Interface
Home-page: https://github.com/jdrumgoole/MongoDB-Atlas-API
Author: Joe Drumgoole
Author-email: joe@joedrumgoole.com
License: Apache 2.0
Platform: UNKNOWN
Classifier: License :: OSI Approved :: Apache Software License
Classifier: Programming Language :: Python
Classifier: Programming Language :: Python :: 3
Classifier: Programming Language :: Python :: 3.6
Classifier: Programming Language :: Python :: Implementation :: CPython
Classifier: Programming Language :: Python :: Implementation :: PyPy
Requires-Python: >=3.6.0
